pyaqua/__init__.py
pyaqua/pyaqua.py
pyaqua-0.2.0.dist-info/LICENSE
pyaqua-0.2.0.dist-info/METADATA
pyaqua-0.2.0.dist-info/WHEEL
pyaqua-0.2.0.dist-info/entry_points.txt
pyaqua-0.2.0.dist-info/top_level.txt
pyaqua-0.2.0.dist-info/RECORD
