Metadata-Version: 2.1
Name: pyaqua
Version: 0.2.0
Summary: Simple CLI for Aqualink.org API
Home-page: https://github.com/samapriya/pyaqua
Author: Samapriya Roy
Author-email: samapriya.roy@gmail.com
License: Apache 2.0
Classifier: Intended Audience :: Developers
Classifier: Intended Audience :: Science/Research
Classifier: Natural Language :: English
Classifier: License :: OSI Approved :: MIT License
Classifier: Programming Language :: Python :: 3.6
Classifier: Programming Language :: Python :: 3.7
Classifier: Operating System :: OS Independent
Classifier: Topic :: Scientific/Engineering :: GIS
License-File: LICENSE
Requires-Dist: requests >=2.23.1
Requires-Dist: pandas >=1.3.3
Requires-Dist: python-dateutil >=2.8.2
Requires-Dist: pytz >=2023.3.post1
Requires-Dist: rapidfuzz >=1.9.0
Requires-Dist: geojson >=2.5.0
Requires-Dist: area >=1.1.1
